lite_captcha/__init__.py
lite_captcha/apps.py
lite_captcha/forms.py
lite_captcha/helpers.py
lite_captcha/templates/lite_captcha/forms/widgets/attrs.html
lite_captcha/templates/lite_captcha/forms/widgets/input.html
lite_captcha-0.0.2.dist-info/LICENSE
lite_captcha-0.0.2.dist-info/METADATA
lite_captcha-0.0.2.dist-info/WHEEL
lite_captcha-0.0.2.dist-info/top_level.txt
lite_captcha-0.0.2.dist-info/RECORD
